centerline/__init__.py
centerline/converters.py
centerline/exceptions.py
centerline/geometry.py
centerline-1.1.1.dist-info/LICENSE
centerline-1.1.1.dist-info/METADATA
centerline-1.1.1.dist-info/WHEEL
centerline-1.1.1.dist-info/entry_points.txt
centerline-1.1.1.dist-info/top_level.txt
centerline-1.1.1.dist-info/RECORD
