Metadata-Version: 2.1
Name: centerline
Version: 1.1.1
Summary: Calculate the centerline of a polygon
Home-page: https://github.com/fitodic/centerline
Download-URL: https://pypi.org/project/centerline/
Author: Filip Todic
Author-email: todic.filip@gmail.com
License: MIT License
Keywords: polygon,centerline,Voronoi
Platform: POSIX
Platform: Microsoft
Platform: MacOS
Classifier: Development Status :: 5 - Production/Stable
Classifier: License :: OSI Approved :: MIT License
Classifier: Operating System :: OS Independent
Classifier: Programming Language :: Python :: 3
Classifier: Programming Language :: Python :: 3.7
Classifier: Programming Language :: Python :: 3.8
Classifier: Programming Language :: Python :: 3.9
Classifier: Programming Language :: Python :: 3.10
Classifier: Programming Language :: Python :: 3.11
Classifier: Intended Audience :: Science/Research
Classifier: Intended Audience :: Developers
Classifier: Topic :: Scientific/Engineering :: GIS
Classifier: Topic :: Scientific/Engineering :: Mathematics
Classifier: Topic :: Scientific/Engineering :: Visualization
Requires-Python: >=3.7
License-File: LICENSE
Requires-Dist: Fiona >=1.7.0
Requires-Dist: Shapely >=1.5.13
Requires-Dist: numpy >=1.10.4
Requires-Dist: scipy >=0.16.1
Requires-Dist: Click >=7.0
Provides-Extra: dev
Requires-Dist: ipdb ; extra == 'dev'
Requires-Dist: tox ; extra == 'dev'
Provides-Extra: docs
Requires-Dist: sphinx ; extra == 'docs'
Provides-Extra: gdal
Requires-Dist: GDAL >=2.3.3 ; extra == 'gdal'
Provides-Extra: lint
Requires-Dist: flake8 ; extra == 'lint'
Requires-Dist: isort ; extra == 'lint'
Requires-Dist: black ; extra == 'lint'
Provides-Extra: test
Requires-Dist: coverage ; extra == 'test'
Requires-Dist: pytest >=4.0.0 ; extra == 'test'
Requires-Dist: pytest-cov ; extra == 'test'
Requires-Dist: pytest-sugar ; extra == 'test'
Requires-Dist: pytest-runner ; extra == 'test'
